rink_plotly/__init__.py
rink_plotly/rink_plot.py
rink_plotly-0.1.0.data/scripts/rink_plot.py
rink_plotly-0.1.0.dist-info/LICENSE
rink_plotly-0.1.0.dist-info/METADATA
rink_plotly-0.1.0.dist-info/WHEEL
rink_plotly-0.1.0.dist-info/top_level.txt
rink_plotly-0.1.0.dist-info/RECORD
