Metadata-Version: 2.1
Name: rink-plotly
Version: 0.1.0
Summary: Package to help plotting a rink using Plotly
Home-page: https://github.com/your_username/your_project_name
Author: Max Tixador
Classifier: Development Status :: 3 - Alpha
Classifier: Intended Audience :: Developers
Classifier: License :: OSI Approved :: MIT License
Classifier: Programming Language :: Python :: 3
Classifier: Programming Language :: Python :: 3.6
Classifier: Programming Language :: Python :: 3.7
Classifier: Programming Language :: Python :: 3.8
Classifier: Programming Language :: Python :: 3.9
Classifier: Programming Language :: Python :: 3.10
Classifier: Programming Language :: Python :: 3.11
License-File: LICENSE
Requires-Dist: numpy
Requires-Dist: plotly
